invrs_opt/__init__.py
invrs_opt/py.typed
invrs_opt/experimental/__init__.py
invrs_opt/experimental/client.py
invrs_opt/experimental/labels.py
invrs_opt/optimizers/__init__.py
invrs_opt/optimizers/base.py
invrs_opt/optimizers/lbfgsb.py
invrs_opt/optimizers/wrapped_optax.py
invrs_opt/parameterization/__init__.py
invrs_opt/parameterization/base.py
invrs_opt/parameterization/filter_project.py
invrs_opt/parameterization/gaussian_levelset.py
invrs_opt/parameterization/pixel.py
invrs_opt/parameterization/transforms.py
invrs_opt-0.12.1.dist-info/licenses/LICENSE
invrs_opt-0.12.1.dist-info/METADATA
invrs_opt-0.12.1.dist-info/WHEEL
invrs_opt-0.12.1.dist-info/top_level.txt
invrs_opt-0.12.1.dist-info/RECORD
