Metadata-Version: 2.4
Name: invrs_opt
Version: 0.12.1
Summary: Algorithms for inverse design
Author-email: "Martin F. Schubert" <mfschubert@gmail.com>
Maintainer-email: "Martin F. Schubert" <mfschubert@gmail.com>
License-Expression: MIT
Keywords: topology,optimization,jax,inverse design
Requires-Python: >=3.7
License-File: LICENSE
Requires-Dist: jax>=0.4.27
Requires-Dist: jaxlib
Requires-Dist: numpy
Requires-Dist: requests
Requires-Dist: optax
Requires-Dist: scipy>=1.15.0
Requires-Dist: totypes
Requires-Dist: types-requests
Provides-Extra: tests
Requires-Dist: parameterized; extra == "tests"
Requires-Dist: pytest; extra == "tests"
Requires-Dist: pytest-cov; extra == "tests"
Requires-Dist: pytest-subtests; extra == "tests"
Provides-Extra: dev
Requires-Dist: bump-my-version; extra == "dev"
Requires-Dist: darglint; extra == "dev"
Requires-Dist: mypy; extra == "dev"
Requires-Dist: pre-commit; extra == "dev"
Dynamic: license-file
